{
  "result": [
    {
      "date": "20 Oktober 2023",
      "day": "Kamis",
      "eventManager": "Malik",
      "place": "Balai RW",
      "time": "9:30 - Selesai"
    },
    {
      "date": "20 Oktober 2023",
      "day": "Kamis",
      "eventManager": "Malik",
      "place": "Balai RW",
      "time": "9:30 - Selesai"
    },
    {
      "date": "20 Oktober 2023",
      "day": "Kamis",
      "eventManager": "Malik",
      "place": "Balai RW",
      "time": "9:30 - Selesai"
    },
    {
      "date": "20 Oktober 2023",
      "day": "Kamis",
      "eventManager": "Malik",
      "place": "Balai RW",
      "time": "9:30 - Selesai"
    }
  ]
}
